py_gis_utility/__init__.py
py_gis_utility/helper.py
py_gis_utility/image_func.py
py_gis_utility/math_func.py
py_gis_utility/ops/__init__.py
py_gis_utility/ops/image_ops.py
py_gis_utility/ops/math_ops.py
py_gis_utility-0.2.2.dist-info/LICENSE
py_gis_utility-0.2.2.dist-info/METADATA
py_gis_utility-0.2.2.dist-info/WHEEL
py_gis_utility-0.2.2.dist-info/top_level.txt
py_gis_utility-0.2.2.dist-info/RECORD
