Metadata-Version: 2.1
Name: py-gis-utility
Version: 0.2.2
Summary: Utility for image and math related operation in GIS
Home-page: https://github.com/fuzailpalnak/py-gis-utility
Author: Fuzail Palnak
Author-email: fuzailpalnak@gmail.com
Keywords: GIS,Image
Classifier: Programming Language :: Python :: 3
Classifier: License :: OSI Approved :: MIT License
Classifier: Topic :: Software Development :: Libraries
Classifier: Topic :: Software Development :: Libraries :: Python Modules
Classifier: Intended Audience :: Developers
Classifier: Operating System :: OS Independent
Requires-Python: ~=3.3
License-File: LICENSE
Requires-Dist: affine (>=2.3.0)
Requires-Dist: numpy (>=1.22.2)
Requires-Dist: opencv-python (==4.5.3.56)
Requires-Dist: scipy (==1.6.2)
Requires-Dist: stitch-n-split (>=0.1.1)
